jupytergis_core/__init__.py
jupytergis_core/_version.py
jupytergis_core/handler.py
jupytergis_core/jgis_ydoc.py
jupytergis_core/schema/__init__.py
jupytergis_core/schema/interfaces/__init__.py
jupytergis_core/schema/interfaces/geojson.py
jupytergis_core/schema/interfaces/export/__init__.py
jupytergis_core/schema/interfaces/export/exportGeoJson.py
jupytergis_core/schema/interfaces/export/exportGeoTiff.py
jupytergis_core/schema/interfaces/processing/__init__.py
jupytergis_core/schema/interfaces/processing/boundingBoxes.py
jupytergis_core/schema/interfaces/processing/buffer.py
jupytergis_core/schema/interfaces/processing/centroids.py
jupytergis_core/schema/interfaces/processing/concaveHull.py
jupytergis_core/schema/interfaces/processing/convexHull.py
jupytergis_core/schema/interfaces/processing/dissolve.py
jupytergis_core/schema/interfaces/project/__init__.py
jupytergis_core/schema/interfaces/project/jgis.py
jupytergis_core/schema/interfaces/project/layers/__init__.py
jupytergis_core/schema/interfaces/project/layers/heatmapLayer.py
jupytergis_core/schema/interfaces/project/layers/hillshadeLayer.py
jupytergis_core/schema/interfaces/project/layers/imageLayer.py
jupytergis_core/schema/interfaces/project/layers/rasterLayer.py
jupytergis_core/schema/interfaces/project/layers/stacLayer.py
jupytergis_core/schema/interfaces/project/layers/storySegmentLayer.py
jupytergis_core/schema/interfaces/project/layers/vectorLayer.py
jupytergis_core/schema/interfaces/project/layers/vectorTileLayer.py
jupytergis_core/schema/interfaces/project/layers/webGlLayer.py
jupytergis_core/schema/interfaces/project/sources/__init__.py
jupytergis_core/schema/interfaces/project/sources/geoJsonSource.py
jupytergis_core/schema/interfaces/project/sources/geoParquetSource.py
jupytergis_core/schema/interfaces/project/sources/geoTiffSource.py
jupytergis_core/schema/interfaces/project/sources/imageSource.py
jupytergis_core/schema/interfaces/project/sources/markerSource.py
jupytergis_core-0.11.1.dist-info/METADATA
jupytergis_core-0.11.1.dist-info/WHEEL
jupytergis_core-0.11.1.dist-info/entry_points.txt
jupytergis_core-0.11.1.dist-info/licenses/LICENSE
jupytergis_core-0.11.1.dist-info/RECORD
