Metadata-Version: 2.4
Name: jupytergis_core
Version: 0.11.1
Dynamic: Keywords
Summary: JupyterGIS core extension
Project-URL: Homepage, https://github.com/geojupyter/jupytergis
Project-URL: Bug Tracker, https://github.com/geojupyter/jupytergis/issues
Project-URL: Repository, https://github.com/geojupyter/jupytergis.git
Author: JupyterGIS contributors
License: BSD 3-Clause License
License-File: LICENSE
Classifier: Framework :: Jupyter
Classifier: Framework :: Jupyter :: JupyterLab
Classifier: Framework :: Jupyter :: JupyterLab :: 4
Classifier: Framework :: Jupyter :: JupyterLab :: Extensions
Classifier: Framework :: Jupyter :: JupyterLab :: Extensions :: Prebuilt
Classifier: License :: OSI Approved :: BSD License
Classifier: Programming Language :: Python
Classifier: Programming Language :: Python :: 3
Classifier: Programming Language :: Python :: 3.10
Classifier: Programming Language :: Python :: 3.11
Classifier: Programming Language :: Python :: 3.12
Classifier: Programming Language :: Python :: 3.13
Classifier: Programming Language :: Python :: 3.14
Classifier: Topic :: Scientific/Engineering :: GIS
Requires-Python: >=3.10
Requires-Dist: jupyter-ydoc<4,>=2
